ocr_joplin_notes/__init__.py
ocr_joplin_notes/cli.py
ocr_joplin_notes/file_ocr.py
ocr_joplin_notes/joplin_api.py
ocr_joplin_notes/joplin_data_wrapper.py
ocr_joplin_notes/ocr_joplin_notes.py
ocr_joplin_notes/rest.py
ocr_joplin_notes/run_ocr.py
ocr_joplin_notes/test.py
ocr_joplin_notes-0.3.12.dist-info/LICENSE
ocr_joplin_notes-0.3.12.dist-info/METADATA
ocr_joplin_notes-0.3.12.dist-info/WHEEL
ocr_joplin_notes-0.3.12.dist-info/top_level.txt
ocr_joplin_notes-0.3.12.dist-info/RECORD
