Metadata-Version: 2.1
Name: ocr-joplin-notes
Version: 0.3.12
Summary: Add OCR data to Joplin notes
Home-page: https://github.com/plamola/ocr-joplin-notes
Author: Matthijs Dekker
Author-email: joplin-development@dekkr.nl
License: MIT
Keywords: ocr-joplin-notes,joplin,ocr-joplin-notes
Platform: UNKNOWN
Requires-Python: >=3.5
License-File: LICENSE
Requires-Dist: numpy (>=1.22.1)
Requires-Dist: setuptools (~=60.7.0)
Requires-Dist: pytz (>=2021.1)
Requires-Dist: nose (>=1.3.7)
Requires-Dist: opencv-python (>=4.5.5.62)
Requires-Dist: click (>=8.0.3)
Requires-Dist: requests (>=2.27.1)
Requires-Dist: PyPDF2 (>=1.26.0)
Requires-Dist: Pillow (>=9.0.0)
Requires-Dist: pdf2image (>=1.16.0)
Requires-Dist: pytesseract (>=0.3.8)
